attention_grabber/__init__.py
attention_grabber/_version.py
attention_grabber-0.1.3.data/data/share/jupyter/labextensions/attention-grabber/build_log.json
attention_grabber-0.1.3.data/data/share/jupyter/labextensions/attention-grabber/package.json
attention_grabber-0.1.3.data/data/share/jupyter/labextensions/attention-grabber/schemas/attention-grabber/package.json.orig
attention_grabber-0.1.3.data/data/share/jupyter/labextensions/attention-grabber/schemas/attention-grabber/plugin.json
attention_grabber-0.1.3.data/data/share/jupyter/labextensions/attention-grabber/static/lib_index_js.20a96b20a0cac5b80c83.js
attention_grabber-0.1.3.data/data/share/jupyter/labextensions/attention-grabber/static/lib_index_js.20a96b20a0cac5b80c83.js.map
attention_grabber-0.1.3.data/data/share/jupyter/labextensions/attention-grabber/static/remoteEntry.b7874f92f9cbc549658d.js
attention_grabber-0.1.3.data/data/share/jupyter/labextensions/attention-grabber/static/remoteEntry.b7874f92f9cbc549658d.js.map
attention_grabber-0.1.3.data/data/share/jupyter/labextensions/attention-grabber/static/style.js
attention_grabber-0.1.3.data/data/share/jupyter/labextensions/attention-grabber/static/style_index_js.19fc81ef6c396de53db8.js
attention_grabber-0.1.3.data/data/share/jupyter/labextensions/attention-grabber/static/style_index_js.19fc81ef6c396de53db8.js.map
attention_grabber-0.1.3.data/data/share/jupyter/labextensions/attention-grabber/install.json
attention_grabber-0.1.3.dist-info/METADATA
attention_grabber-0.1.3.dist-info/WHEEL
attention_grabber-0.1.3.dist-info/licenses/LICENSE
attention_grabber-0.1.3.dist-info/RECORD
