Metadata-Version: 2.1
Name: attention_grabber
Version: 0.1.3
Summary: Flashes your screen when cells are finished, until you click on the notebook again.
Project-URL: Homepage, https://github.com/natemacfadden/jupyterlab_attention-grabber
Project-URL: Bug Tracker, https://github.com/natemacfadden/jupyterlab_attention-grabber/issues
Project-URL: Repository, https://github.com/natemacfadden/jupyterlab_attention-grabber.git
Author-email: Nate MacFadden <natemacfadden@gmail.com>
License: BSD 3-Clause License
License-File: LICENSE
Classifier: Framework :: Jupyter
Classifier: Framework :: Jupyter :: JupyterLab
Classifier: Framework :: Jupyter :: JupyterLab :: 4
Classifier: Framework :: Jupyter :: JupyterLab :: Extensions
Classifier: Framework :: Jupyter :: JupyterLab :: Extensions :: Prebuilt
Classifier: License :: OSI Approved :: BSD License
Classifier: Programming Language :: Python
Classifier: Programming Language :: Python :: 3
Classifier: Programming Language :: Python :: 3.8
Classifier: Programming Language :: Python :: 3.9
Classifier: Programming Language :: Python :: 3.10
Classifier: Programming Language :: Python :: 3.11
Classifier: Programming Language :: Python :: 3.12
Requires-Python: >=3.8
